{
    "swagger": "2.0",
    "info": {
        "contact": {}
    },
    "paths": {
        "/buy-actions/buy-cart": {
            "post": {
                "description": "buy cart",
                "consumes": [
                    "application/json"
                ],
                "produces": [
                    "application/json"
                ],
                "tags": [
                    "buy-service"
                ],
                "parameters": [
                    {
                        "description": "Cart data",
                        "name": "cart",
                        "in": "body",
                        "required": true,
                        "schema": {
                            "$ref": "#/definitions/main.Cart"
                        }
                    }
                ],
                "responses": {
                    "200": {
                        "description": "OK",
                        "schema": {
                            "type": "string"
                        }
                    }
                }
            }
        }
    },
    "definitions": {
        "main.Cart": {
            "type": "object"
        }
    }
}