{
    "swagger": "2.0",
    "info": {
        "contact": {}
    },
    "paths": {
        "/user-service/": {
            "put": {
                "description": "add user",
                "consumes": [
                    "application/json"
                ],
                "produces": [
                    "application/json"
                ],
                "tags": [
                    "user-service"
                ],
                "responses": {
                    "200": {
                        "description": "OK",
                        "schema": {
                            "type": "string"
                        }
                    }
                }
            },
            "patch": {
                "description": "update user",
                "consumes": [
                    "application/json"
                ],
                "produces": [
                    "application/json"
                ],
                "tags": [
                    "user-service"
                ],
                "responses": {
                    "200": {
                        "description": "OK",
                        "schema": {
                            "type": "string"
                        }
                    }
                }
            }
        },
        "/user-service/get-all": {
            "get": {
                "description": "description of function that get all users from DB",
                "consumes": [
                    "application/json"
                ],
                "produces": [
                    "application/json"
                ],
                "tags": [
                    "user-service"
                ],
                "summary": "GetAll",
                "responses": {
                    "200": {
                        "description": "OK",
                        "schema": {
                            "type": "string"
                        }
                    }
                }
            }
        },
        "/user-service/spend-money": {
            "post": {
                "description": "spend money",
                "consumes": [
                    "application/json"
                ],
                "tags": [
                    "user-service"
                ],
                "parameters": [
                    {
                        "type": "string",
                        "description": "Some ID",
                        "name": "id",
                        "in": "query"
                    },
                    {
                        "type": "integer",
                        "description": "Some money",
                        "name": "money",
                        "in": "query"
                    }
                ],
                "responses": {
                    "200": {
                        "description": "OK",
                        "schema": {
                            "type": "string"
                        }
                    }
                }
            }
        },
        "/user-service/test": {
            "get": {
                "description": "do ping",
                "consumes": [
                    "application/json"
                ],
                "produces": [
                    "application/json"
                ],
                "tags": [
                    "user-service"
                ],
                "summary": "ping example",
                "responses": {
                    "200": {
                        "description": "OK",
                        "schema": {
                            "type": "string"
                        }
                    }
                }
            }
        },
        "/user-service/wallet-replenishment": {
            "post": {
                "description": "add money",
                "consumes": [
                    "application/json"
                ],
                "tags": [
                    "user-service"
                ],
                "parameters": [
                    {
                        "type": "string",
                        "description": "Some ID",
                        "name": "id",
                        "in": "query"
                    },
                    {
                        "type": "integer",
                        "description": "Some money",
                        "name": "money",
                        "in": "query"
                    }
                ],
                "responses": {
                    "200": {
                        "description": "OK",
                        "schema": {
                            "type": "string"
                        }
                    }
                }
            }
        },
        "/user-service/{id}": {
            "get": {
                "description": "description of function that get user by id",
                "consumes": [
                    "application/json"
                ],
                "produces": [
                    "application/json"
                ],
                "tags": [
                    "user-service"
                ],
                "parameters": [
                    {
                        "type": "string",
                        "description": "Some ID",
                        "name": "id",
                        "in": "path",
                        "required": true
                    }
                ],
                "responses": {
                    "200": {
                        "description": "OK",
                        "schema": {
                            "type": "string"
                        }
                    }
                }
            },
            "delete": {
                "description": "delete user",
                "consumes": [
                    "application/json"
                ],
                "produces": [
                    "application/json"
                ],
                "tags": [
                    "user-service"
                ],
                "parameters": [
                    {
                        "type": "string",
                        "description": "Some ID",
                        "name": "id",
                        "in": "path",
                        "required": true
                    }
                ],
                "responses": {
                    "200": {
                        "description": "OK",
                        "schema": {
                            "type": "string"
                        }
                    }
                }
            }
        }
    }
}